rplayground_mcp/__init__.py
rplayground_mcp/cli_basic.py
rplayground_mcp/configuration.py
rplayground_mcp/mcp_cli.py
rplayground_mcp/prompts.py
rplayground_mcp/session_manager.py
rplayground_mcp/session_manager_interface.py
rplayground_mcp/utils.py
mseep_rplayground_mcp-0.1.3.dist-info/METADATA
mseep_rplayground_mcp-0.1.3.dist-info/WHEEL
mseep_rplayground_mcp-0.1.3.dist-info/entry_points.txt
mseep_rplayground_mcp-0.1.3.dist-info/top_level.txt
mseep_rplayground_mcp-0.1.3.dist-info/RECORD
