Metadata-Version: 2.4
Name: mseep-rplayground-mcp
Version: 0.1.3
Summary: An MCP that lets the model transiently execute R code.
Author-email: mseep <support@skydeck.ai>
Requires-Python: >=3.10
Requires-Dist: anyio>=4.9.0
Requires-Dist: mcp[cli]>=1.6.0
Requires-Dist: pillow>=10.0
Requires-Dist: pytest-asyncio>=0.26.0
Requires-Dist: pytest>=8.3.5
Requires-Dist: rpy2>=3.5.17
Requires-Dist: packaging>=24.2
Requires-Dist: pydantic-settings>=2.8.1
